[
  {
    "id": "ST29-001",
    "pack_id": "569029",
    "name": "Monkey.D.Luffy",
    "rarity": "Leader",
    "category": "Leader",
    "img_url": "../images/cardlist/card/ST29-001.png?260410",
    "img_full_url": "https://en.onepiece-cardgame.com/images/cardlist/card/ST29-001.png?260410",
    "cost": 6,
    "attributes": [
      "Strike"
    ],
    "power": 5000,
    "counter": null,
    "colors": [
      "Yellow"
    ],
    "block_number": 4,
    "types": [
      "Egghead",
      "The Four Emperors",
      "Straw Hat Crew"
    ],
    "effect": "[When Attacking] If you have 2 or less Life cards, draw 1 card and trash 1 card from your hand.",
    "trigger": null,
    "tile_set_id": "ST29",
    "variants": [
      {
        "id": "ST29-001_p1",
        "img_url": "../images/cardlist/card/ST29-001_p1.png?260410",
        "img_full_url": "https://en.onepiece-cardgame.com/images/cardlist/card/ST29-001_p1.png?260410",
        "rarity": "Leader"
      }
    ]
  },
  {
    "id": "ST29-002",
    "pack_id": "569029",
    "name": "Usopp",
    "rarity": "Common",
    "category": "Character",
    "img_url": "../images/cardlist/card/ST29-002.png?260410",
    "img_full_url": "https://en.onepiece-cardgame.com/images/cardlist/card/ST29-002.png?260410",
    "cost": 3,
    "attributes": [
      "Ranged"
    ],
    "power": 4000,
    "counter": 1000,
    "colors": [
      "Yellow"
    ],
    "block_number": 4,
    "types": [
      "Egghead",
      "Straw Hat Crew"
    ],
    "effect": "[On Play]/[When Attacking] Rest up to 1 of your opponent's Characters with a cost equal to or less than the number of your opponent's Life cards.",
    "trigger": null,
    "tile_set_id": "ST29",
    "variants": [
      {
        "id": "ST29-002_p1",
        "img_url": "../images/cardlist/card/ST29-002_p1.png?260410",
        "img_full_url": "https://en.onepiece-cardgame.com/images/cardlist/card/ST29-002_p1.png?260410",
        "rarity": "Common"
      }
    ]
  },
  {
    "id": "ST29-003",
    "pack_id": "569029",
    "name": "Kaku",
    "rarity": "Common",
    "category": "Character",
    "img_url": "../images/cardlist/card/ST29-003.png?260410",
    "img_full_url": "https://en.onepiece-cardgame.com/images/cardlist/card/ST29-003.png?260410",
    "cost": 4,
    "attributes": [
      "Slash"
    ],
    "power": 5000,
    "counter": 1000,
    "colors": [
      "Yellow"
    ],
    "block_number": 4,
    "types": [
      "Egghead",
      "CP0"
    ],
    "effect": "If the number of your Life cards is equal to or less than the number of your opponent's Life cards, this Character gains +1000 power.",
    "trigger": "[Trigger] K.O. up to 1 of your opponent's Characters with a cost of 3 or less.",
    "tile_set_id": "ST29",
    "variants": [
      {
        "id": "ST29-003_p1",
        "img_url": "../images/cardlist/card/ST29-003_p1.png?260410",
        "img_full_url": "https://en.onepiece-cardgame.com/images/cardlist/card/ST29-003_p1.png?260410",
        "rarity": "Common"
      }
    ]
  },
  {
    "id": "ST29-004",
    "pack_id": "569029",
    "name": "Sanji",
    "rarity": "SuperRare",
    "category": "Character",
    "img_url": "../images/cardlist/card/ST29-004.png?260410",
    "img_full_url": "https://en.onepiece-cardgame.com/images/cardlist/card/ST29-004.png?260410",
    "cost": 4,
    "attributes": [
      "Strike"
    ],
    "power": 5000,
    "counter": 1000,
    "colors": [
      "Yellow"
    ],
    "block_number": 4,
    "types": [
      "Egghead",
      "Straw Hat Crew"
    ],
    "effect": "[On Play] Look at 4 cards from the top of your deck; reveal up to 1 {Straw Hat Crew} type card and add it to your hand. Then, place the rest at the bottom of your deck in any order.",
    "trigger": "[Trigger] You may trash 1 card from your hand: Play this card.",
    "tile_set_id": "ST29",
    "variants": [
      {
        "id": "ST29-004_p1",
        "img_url": "../images/cardlist/card/ST29-004_p1.png?260410",
        "img_full_url": "https://en.onepiece-cardgame.com/images/cardlist/card/ST29-004_p1.png?260410",
        "rarity": "SuperRare"
      }
    ]
  },
  {
    "id": "ST29-005",
    "pack_id": "569029",
    "name": "Jinbe",
    "rarity": "Common",
    "category": "Character",
    "img_url": "../images/cardlist/card/ST29-005.png?260410",
    "img_full_url": "https://en.onepiece-cardgame.com/images/cardlist/card/ST29-005.png?260410",
    "cost": 6,
    "attributes": [
      "Strike"
    ],
    "power": 5000,
    "counter": 2000,
    "colors": [
      "Yellow"
    ],
    "block_number": 4,
    "types": [
      "Fish-Man",
      "Egghead",
      "Straw Hat Crew"
    ],
    "effect": "-",
    "trigger": "[Trigger] If your Leader is [Monkey.D.Luffy], play this card.",
    "tile_set_id": "ST29",
    "variants": [
      {
        "id": "ST29-005_p1",
        "img_url": "../images/cardlist/card/ST29-005_p1.png?260410",
        "img_full_url": "https://en.onepiece-cardgame.com/images/cardlist/card/ST29-005_p1.png?260410",
        "rarity": "Common"
      }
    ]
  },
  {
    "id": "ST29-006",
    "pack_id": "569029",
    "name": "Stussy",
    "rarity": "Common",
    "category": "Character",
    "img_url": "../images/cardlist/card/ST29-006.png?260410",
    "img_full_url": "https://en.onepiece-cardgame.com/images/cardlist/card/ST29-006.png?260410",
    "cost": 6,
    "attributes": [
      "Special"
    ],
    "power": 7000,
    "counter": 2000,
    "colors": [
      "Yellow"
    ],
    "block_number": 4,
    "types": [
      "Egghead"
    ],
    "effect": "-",
    "trigger": null,
    "tile_set_id": "ST29",
    "variants": [
      {
        "id": "ST29-006_p1",
        "img_url": "../images/cardlist/card/ST29-006_p1.png?260410",
        "img_full_url": "https://en.onepiece-cardgame.com/images/cardlist/card/ST29-006_p1.png?260410",
        "rarity": "Common"
      }
    ]
  },
  {
    "id": "ST29-007",
    "pack_id": "569029",
    "name": "Tony Tony.Chopper",
    "rarity": "Common",
    "category": "Character",
    "img_url": "../images/cardlist/card/ST29-007.png?260410",
    "img_full_url": "https://en.onepiece-cardgame.com/images/cardlist/card/ST29-007.png?260410",
    "cost": 4,
    "attributes": [
      "Wisdom"
    ],
    "power": 5000,
    "counter": 1000,
    "colors": [
      "Yellow"
    ],
    "block_number": 4,
    "types": [
      "Animal",
      "Egghead",
      "Straw Hat Crew"
    ],
    "effect": "[On K.O.] You may add 1 card from the top or bottom of your Life cards to your hand: Add up to 1 card from your hand to the top of your Life cards.",
    "trigger": "[Trigger] Up to 1 of your [Monkey.D.Luffy] cards gains +2000 power during this turn.",
    "tile_set_id": "ST29",
    "variants": [
      {
        "id": "ST29-007_p1",
        "img_url": "../images/cardlist/card/ST29-007_p1.png?260410",
        "img_full_url": "https://en.onepiece-cardgame.com/images/cardlist/card/ST29-007_p1.png?260410",
        "rarity": "Common"
      }
    ]
  },
  {
    "id": "ST29-008",
    "pack_id": "569029",
    "name": "Nami",
    "rarity": "Common",
    "category": "Character",
    "img_url": "../images/cardlist/card/ST29-008.png?260410",
    "img_full_url": "https://en.onepiece-cardgame.com/images/cardlist/card/ST29-008.png?260410",
    "cost": 3,
    "attributes": [
      "Special"
    ],
    "power": 1000,
    "counter": 1000,
    "colors": [
      "Yellow"
    ],
    "block_number": 4,
    "types": [
      "Egghead",
      "Straw Hat Crew"
    ],
    "effect": "If your {Egghead} type Character would be K.O.'d by your opponent's effect, you may turn 1 card from the top of your Life cards face-up instead.",
    "trigger": "[Trigger] If your Leader is [Monkey.D.Luffy], play this card.",
    "tile_set_id": "ST29",
    "variants": [
      {
        "id": "ST29-008_p1",
        "img_url": "../images/cardlist/card/ST29-008_p1.png?260410",
        "img_full_url": "https://en.onepiece-cardgame.com/images/cardlist/card/ST29-008_p1.png?260410",
        "rarity": "Common"
      }
    ]
  },
  {
    "id": "ST29-009",
    "pack_id": "569029",
    "name": "Nico Robin",
    "rarity": "Common",
    "category": "Character",
    "img_url": "../images/cardlist/card/ST29-009.png?260410",
    "img_full_url": "https://en.onepiece-cardgame.com/images/cardlist/card/ST29-009.png?260410",
    "cost": 4,
    "attributes": [
      "Strike"
    ],
    "power": 2000,
    "counter": 2000,
    "colors": [
      "Yellow"
    ],
    "block_number": 4,
    "types": [
      "Egghead",
      "Straw Hat Crew"
    ],
    "effect": "[Blocker] (After your opponent declares an attack, you may rest this card to make it the new target of the attack.)",
    "trigger": "[Trigger] If your Leader is [Monkey.D.Luffy], play this card.",
    "tile_set_id": "ST29",
    "variants": [
      {
        "id": "ST29-009_p1",
        "img_url": "../images/cardlist/card/ST29-009_p1.png?260410",
        "img_full_url": "https://en.onepiece-cardgame.com/images/cardlist/card/ST29-009_p1.png?260410",
        "rarity": "Common"
      }
    ]
  },
  {
    "id": "ST29-010",
    "pack_id": "569029",
    "name": "Franky",
    "rarity": "Common",
    "category": "Character",
    "img_url": "../images/cardlist/card/ST29-010.png?260410",
    "img_full_url": "https://en.onepiece-cardgame.com/images/cardlist/card/ST29-010.png?260410",
    "cost": 5,
    "attributes": [
      "Ranged"
    ],
    "power": 6000,
    "counter": 2000,
    "colors": [
      "Yellow"
    ],
    "block_number": 4,
    "types": [
      "Egghead",
      "Straw Hat Crew"
    ],
    "effect": "-",
    "trigger": null,
    "tile_set_id": "ST29",
    "variants": [
      {
        "id": "ST29-010_p1",
        "img_url": "../images/cardlist/card/ST29-010_p1.png?260410",
        "img_full_url": "https://en.onepiece-cardgame.com/images/cardlist/card/ST29-010_p1.png?260410",
        "rarity": "Common"
      }
    ]
  },
  {
    "id": "ST29-011",
    "pack_id": "569029",
    "name": "Brook",
    "rarity": "Common",
    "category": "Character",
    "img_url": "../images/cardlist/card/ST29-011.png?260410",
    "img_full_url": "https://en.onepiece-cardgame.com/images/cardlist/card/ST29-011.png?260410",
    "cost": 2,
    "attributes": [
      "Slash"
    ],
    "power": 2000,
    "counter": 1000,
    "colors": [
      "Yellow"
    ],
    "block_number": 4,
    "types": [
      "Egghead",
      "Straw Hat Crew"
    ],
    "effect": "[Blocker] (After your opponent declares an attack, you may rest this card to make it the new target of the attack.)",
    "trigger": null,
    "tile_set_id": "ST29",
    "variants": [
      {
        "id": "ST29-011_p1",
        "img_url": "../images/cardlist/card/ST29-011_p1.png?260410",
        "img_full_url": "https://en.onepiece-cardgame.com/images/cardlist/card/ST29-011_p1.png?260410",
        "rarity": "Common"
      }
    ]
  },
  {
    "id": "ST29-012",
    "pack_id": "569029",
    "name": "Monkey.D.Luffy",
    "rarity": "Common",
    "category": "Character",
    "img_url": "../images/cardlist/card/ST29-012.png?260410",
    "img_full_url": "https://en.onepiece-cardgame.com/images/cardlist/card/ST29-012.png?260410",
    "cost": 1,
    "attributes": [
      "Strike"
    ],
    "power": null,
    "counter": 1000,
    "colors": [
      "Yellow"
    ],
    "block_number": 4,
    "types": [
      "Egghead",
      "The Four Emperors",
      "Straw Hat Crew"
    ],
    "effect": "[Activate: Main] [Once Per Turn] Give up to 1 rested DON!! card to 1 of your [Monkey.D.Luffy] cards.",
    "trigger": "[Trigger] Play this card.",
    "tile_set_id": "ST29",
    "variants": [
      {
        "id": "ST29-012_p1",
        "img_url": "../images/cardlist/card/ST29-012_p1.png?260410",
        "img_full_url": "https://en.onepiece-cardgame.com/images/cardlist/card/ST29-012_p1.png?260410",
        "rarity": "Common"
      }
    ]
  },
  {
    "id": "ST29-013",
    "pack_id": "569029",
    "name": "Rob Lucci",
    "rarity": "Common",
    "category": "Character",
    "img_url": "../images/cardlist/card/ST29-013.png?260410",
    "img_full_url": "https://en.onepiece-cardgame.com/images/cardlist/card/ST29-013.png?260410",
    "cost": 5,
    "attributes": [
      "Strike"
    ],
    "power": 6000,
    "counter": 1000,
    "colors": [
      "Yellow"
    ],
    "block_number": 4,
    "types": [
      "Egghead",
      "CP0"
    ],
    "effect": "-",
    "trigger": "[Trigger] K.O. up to 1 of your opponent's Characters with a cost equal to or less than the total of your and your opponent's Life cards.",
    "tile_set_id": "ST29",
    "variants": [
      {
        "id": "ST29-013_p1",
        "img_url": "../images/cardlist/card/ST29-013_p1.png?260410",
        "img_full_url": "https://en.onepiece-cardgame.com/images/cardlist/card/ST29-013_p1.png?260410",
        "rarity": "Common"
      }
    ]
  },
  {
    "id": "ST29-014",
    "pack_id": "569029",
    "name": "Roronoa Zoro",
    "rarity": "SuperRare",
    "category": "Character",
    "img_url": "../images/cardlist/card/ST29-014.png?260410",
    "img_full_url": "https://en.onepiece-cardgame.com/images/cardlist/card/ST29-014.png?260410",
    "cost": 6,
    "attributes": [
      "Slash"
    ],
    "power": 8000,
    "counter": null,
    "colors": [
      "Yellow"
    ],
    "block_number": 4,
    "types": [
      "Egghead",
      "Straw Hat Crew"
    ],
    "effect": "[Rush: Character] (This card can attack Characters on the turn in which it is played.)<br>[Activate: Main] [Once Per Turn] You may trash 1 card with a [Trigger] from your hand: Draw 1 card and give up to 1 rested DON!! card to your Leader or 1 of your Characters.",
    "trigger": null,
    "tile_set_id": "ST29",
    "variants": [
      {
        "id": "ST29-014_p1",
        "img_url": "../images/cardlist/card/ST29-014_p1.png?260410",
        "img_full_url": "https://en.onepiece-cardgame.com/images/cardlist/card/ST29-014_p1.png?260410",
        "rarity": "SuperRare"
      }
    ]
  },
  {
    "id": "ST29-015",
    "pack_id": "569029",
    "name": "Raw Heat Strike",
    "rarity": "Common",
    "category": "Event",
    "img_url": "../images/cardlist/card/ST29-015.png?260410",
    "img_full_url": "https://en.onepiece-cardgame.com/images/cardlist/card/ST29-015.png?260410",
    "cost": 1,
    "attributes": [],
    "power": null,
    "counter": null,
    "colors": [
      "Yellow"
    ],
    "block_number": 4,
    "types": [
      "Egghead",
      "Straw Hat Crew"
    ],
    "effect": "[Counter] Up to 1 of your Leader or Character cards gains +2000 power during this battle. Then, if you have 1 or less Life cards, give up to 1 of your opponent's Leader or Character cards −2000 power during this turn.",
    "trigger": "[Trigger] Draw 1 card.",
    "tile_set_id": "ST29",
    "variants": []
  },
  {
    "id": "ST29-016",
    "pack_id": "569029",
    "name": "Kizaru!! Compared to Two Years Ago We're a Hundred Times Stronger Now!!",
    "rarity": "Common",
    "category": "Event",
    "img_url": "../images/cardlist/card/ST29-016.png?260410",
    "img_full_url": "https://en.onepiece-cardgame.com/images/cardlist/card/ST29-016.png?260410",
    "cost": 1,
    "attributes": [],
    "power": null,
    "counter": null,
    "colors": [
      "Yellow"
    ],
    "block_number": 4,
    "types": [
      "Egghead",
      "The Four Emperors",
      "Straw Hat Crew"
    ],
    "effect": "[Main] Your [Monkey.D.Luffy] Leader gains [Unblockable] during this turn.<br>(This card cannot be blocked.)<br>[Counter] Your Leader gains +3000 power during this battle.",
    "trigger": null,
    "tile_set_id": "ST29",
    "variants": []
  },
  {
    "id": "ST29-017",
    "pack_id": "569029",
    "name": "Iai Death Lion Song",
    "rarity": "Common",
    "category": "Event",
    "img_url": "../images/cardlist/card/ST29-017.png?260410",
    "img_full_url": "https://en.onepiece-cardgame.com/images/cardlist/card/ST29-017.png?260410",
    "cost": 2,
    "attributes": [],
    "power": null,
    "counter": null,
    "colors": [
      "Yellow"
    ],
    "block_number": 4,
    "types": [
      "Egghead",
      "Straw Hat Crew"
    ],
    "effect": "[Counter] Up to 1 of your Leader or Character cards gains +4000 power during this battle. Then, if you have 2 or less Life cards, K.O. up to 1 of your opponent's Characters with a cost of 3 or less.",
    "trigger": "[Trigger] Draw 2 cards and trash 1 card from your hand.",
    "tile_set_id": "ST29",
    "variants": []
  }
]